{
    "id": "https://api.weather.gov/alerts/NWS-IDP-PROD-3996300-3390844",
    "type": "Feature",
    "geometry": null,
    "properties": {
        "@id": "https://api.weather.gov/alerts/NWS-IDP-PROD-3996300-3390844",
        "@type": "wx:Alert",
        "id": "NWS-IDP-PROD-3996300-3390844",
        "areaDesc": "Wayne; Williamson; Perry; Hardin; Warrick; Jefferson; McCracken; Stoddard; Mississippi; Ripley; Gibson; Carter; Johnson; Pulaski; Bollinger; Edwards; Hamilton; Livingston; Gallatin; Union; Pike; Perry; Saline; Alexander; Vanderburgh; Henderson; Massac; Union; Scott; Ballard; Jackson; Butler; Posey; Franklin; Cape Girardeau; Pope; White; New Madrid; Crittenden; Carlisle; Wabash; Wayne",
        "geocode": {
            "UGC": [
                "MOZ100",
                "ILZ085",
                "MOZ076",
                "ILZ091",
                "INZ087",
                "ILZ075",
                "KYZ005",
                "MOZ110",
                "MOZ112",
                "MOZ108",
                "INZ081",
                "MOZ107",
                "ILZ089",
                "ILZ093",
                "MOZ086",
                "ILZ077",
                "ILZ082",
                "KYZ007",
                "ILZ087",
                "KYZ014",
                "INZ082",
                "ILZ080",
                "ILZ086",
                "ILZ092",
                "INZ086",
                "KYZ018",
                "ILZ094",
                "ILZ088",
                "MOZ111",
                "KYZ004",
                "ILZ084",
                "MOZ109",
                "INZ085",
                "ILZ081",
                "MOZ087",
                "ILZ090",
                "ILZ083",
                "MOZ114",
                "KYZ010",
                "KYZ003",
                "ILZ078",
                "ILZ076"
            ],
            "SAME": [
                "029223",
                "017199",
                "029157",
                "017069",
                "018173",
                "017081",
                "021145",
                "029207",
                "029133",
                "029181",
                "018051",
                "029035",
                "017087",
                "017153",
                "029017",
                "017047",
                "017065",
                "021139",
                "017059",
                "021225",
                "018125",
                "017145",
                "017165",
                "017003",
                "018163",
                "021101",
                "017127",
                "017181",
                "029201",
                "021007",
                "017077",
                "029023",
                "018129",
                "017055",
                "029031",
                "017151",
                "017193",
                "029143",
                "021055",
                "021039",
                "017185",
                "017191"
            ]
        },
        "affectedZones": [
            "https://api.weather.gov/zones/forecast/MOZ100",
            "https://api.weather.gov/zones/forecast/ILZ085",
            "https://api.weather.gov/zones/forecast/MOZ076",
            "https://api.weather.gov/zones/forecast/ILZ091",
            "https://api.weather.gov/zones/forecast/INZ087",
            "https://api.weather.gov/zones/forecast/ILZ075",
            "https://api.weather.gov/zones/forecast/KYZ005",
            "https://api.weather.gov/zones/forecast/MOZ110",
            "https://api.weather.gov/zones/forecast/MOZ112",
            "https://api.weather.gov/zones/forecast/MOZ108",
            "https://api.weather.gov/zones/forecast/INZ081",
            "https://api.weather.gov/zones/forecast/MOZ107",
            "https://api.weather.gov/zones/forecast/ILZ089",
            "https://api.weather.gov/zones/forecast/ILZ093",
            "https://api.weather.gov/zones/forecast/MOZ086",
            "https://api.weather.gov/zones/forecast/ILZ077",
            "https://api.weather.gov/zones/forecast/ILZ082",
            "https://api.weather.gov/zones/forecast/KYZ007",
            "https://api.weather.gov/zones/forecast/ILZ087",
            "https://api.weather.gov/zones/forecast/KYZ014",
            "https://api.weather.gov/zones/forecast/INZ082",
            "https://api.weather.gov/zones/forecast/ILZ080",
            "https://api.weather.gov/zones/forecast/ILZ086",
            "https://api.weather.gov/zones/forecast/ILZ092",
            "https://api.weather.gov/zones/forecast/INZ086",
            "https://api.weather.gov/zones/forecast/KYZ018",
            "https://api.weather.gov/zones/forecast/ILZ094",
            "https://api.weather.gov/zones/forecast/ILZ088",
            "https://api.weather.gov/zones/forecast/MOZ111",
            "https://api.weather.gov/zones/forecast/KYZ004",
            "https://api.weather.gov/zones/forecast/ILZ084",
            "https://api.weather.gov/zones/forecast/MOZ109",
            "https://api.weather.gov/zones/forecast/INZ085",
            "https://api.weather.gov/zones/forecast/ILZ081",
            "https://api.weather.gov/zones/forecast/MOZ087",
            "https://api.weather.gov/zones/forecast/ILZ090",
            "https://api.weather.gov/zones/forecast/ILZ083",
            "https://api.weather.gov/zones/forecast/MOZ114",
            "https://api.weather.gov/zones/forecast/KYZ010",
            "https://api.weather.gov/zones/forecast/KYZ003",
            "https://api.weather.gov/zones/forecast/ILZ078",
            "https://api.weather.gov/zones/forecast/ILZ076"
        ],
        "references": [
            {
                "@id": "https://api.weather.gov/alerts/NWS-IDP-PROD-3994494-3389440",
                "identifier": "NWS-IDP-PROD-3994494-3389440",
                "sender": "w-nws.webmaster@noaa.gov",
                "sent": "2020-01-09T02:13:00-06:00"
            },
            {
                "@id": "https://api.weather.gov/alerts/NWS-IDP-PROD-3993909-3388969",
                "identifier": "NWS-IDP-PROD-3993909-3388969",
                "sender": "w-nws.webmaster@noaa.gov",
                "sent": "2020-01-08T14:59:00-06:00"
            },
            {
                "@id": "https://api.weather.gov/alerts/NWS-IDP-PROD-3994493-3389439",
                "identifier": "NWS-IDP-PROD-3994493-3389439",
                "sender": "w-nws.webmaster@noaa.gov",
                "sent": "2020-01-09T02:13:00-06:00"
            },
            {
                "@id": "https://api.weather.gov/alerts/NWS-IDP-PROD-3995485-3390188",
                "identifier": "NWS-IDP-PROD-3995485-3390188",
                "sender": "w-nws.webmaster@noaa.gov",
                "sent": "2020-01-09T14:54:00-06:00"
            },
            {
                "@id": "https://api.weather.gov/alerts/NWS-IDP-PROD-3995484-3390187",
                "identifier": "NWS-IDP-PROD-3995484-3390187",
                "sender": "w-nws.webmaster@noaa.gov",
                "sent": "2020-01-09T14:54:00-06:00"
            }
        ],
        "sent": "2020-01-10T02:22:00-06:00",
        "effective": "2020-01-10T02:22:00-06:00",
        "onset": "2020-01-10T18:00:00-06:00",
        "expires": "2020-01-10T16:00:00-06:00",
        "ends": "2020-01-11T15:00:00-06:00",
        "status": "Actual",
        "messageType": "Update",
        "category": "Met",
        "severity": "Severe",
        "certainty": "Possible",
        "urgency": "Future",
        "event": "Flash Flood Watch",
        "sender": "w-nws.webmaster@noaa.gov",
        "senderName": "NWS Paducah KY",
        "headline": "Flash Flood Watch issued January 10 at 2:22AM CST until January 11 at 3:00PM CST by NWS Paducah KY",
        "description": "The Flash Flood Watch continues for\n\n* Portions of southern Illinois, southwest Indiana, western\nKentucky, and southeast Missouri, including the following\nareas, in southern Illinois, Alexander, Edwards, Franklin,\nGallatin, Hamilton, Hardin, Jackson, Jefferson, Johnson,\nMassac, Perry IL, Pope, Pulaski, Saline, Union, Wabash, Wayne\nIL, White, and Williamson. In southwest Indiana, Gibson, Pike,\nPosey, Vanderburgh, and Warrick. In western Kentucky, Ballard,\nCarlisle, Crittenden, Henderson, Livingston, McCracken, and\nUnion KY. In southeast Missouri, Bollinger, Butler, Cape\nGirardeau, Carter, Mississippi, New Madrid, Perry MO, Ripley,\nScott, Stoddard, and Wayne MO.\n\n* From this evening through Saturday afternoon\n\n* Periods of heavy rain are expected Friday night into Saturday.\nThe heaviest rains will be between midnight Friday night and\nnoon on Saturday. Storm total rainfall by late Saturday\nafternoon will likely average from 3 to 4 inches. Locally higher\namounts are possible.\n\n* Rapid rises in creeks and streams are expected. Low water\ncrossings may become impassable. Look for flood prone areas to\nbecome inundated.",
        "instruction": "A Flash Flood Watch means that conditions may develop that lead\nto flash flooding. Flash flooding is a very dangerous situation.\n\nYou should monitor later forecasts and be prepared to take action\nshould Flash Flood Warnings be issued.",
        "response": "Monitor",
        "parameters": {
            "NWSheadline": [
                "FLASH FLOOD WATCH REMAINS IN EFFECT FROM THIS EVENING THROUGH SATURDAY AFTERNOON"
            ],
            "VTEC": [
                "/O.CON.KPAH.FF.A.0001.200111T0000Z-200111T2100Z/"
            ],
            "EAS-ORG": [
                "WXR"
            ],
            "PIL": [
                "PAHFFAPAH"
            ],
            "BLOCKCHANNEL": [
                "CMAS",
                "EAS",
                "NWEM"
            ],
            "eventEndingTime": [
                "2020-01-11T15:00:00-06:00"
            ]
        }
    }
}