{
    "id": "https://api.weather.gov/alerts/NWS-IDP-PROD-4036682-3425569",
    "type": "Feature",
    "geometry": null,
    "properties": {
        "@id": "https://api.weather.gov/alerts/NWS-IDP-PROD-4036682-3425569",
        "@type": "wx:Alert",
        "id": "NWS-IDP-PROD-4036682-3425569",
        "areaDesc": "Los Angeles County San Fernando Valley",
        "geocode": {
            "UGC": [
                "CAZ547"
            ],
            "SAME": [
                "006037"
            ]
        },
        "affectedZones": [
            "https://api.weather.gov/zones/forecast/CAZ547"
        ],
        "references": [
            {
                "@id": "https://api.weather.gov/alerts/NWS-IDP-PROD-4035691-3424555",
                "identifier": "NWS-IDP-PROD-4035691-3424555",
                "sender": "w-nws.webmaster@noaa.gov",
                "sent": "2020-02-02T16:05:00-08:00"
            },
            {
                "@id": "https://api.weather.gov/alerts/NWS-IDP-PROD-4035691-3424557",
                "identifier": "NWS-IDP-PROD-4035691-3424557",
                "sender": "w-nws.webmaster@noaa.gov",
                "sent": "2020-02-02T16:05:00-08:00"
            },
            {
                "@id": "https://api.weather.gov/alerts/NWS-IDP-PROD-4035691-3424556",
                "identifier": "NWS-IDP-PROD-4035691-3424556",
                "sender": "w-nws.webmaster@noaa.gov",
                "sent": "2020-02-02T16:05:00-08:00"
            },
            {
                "@id": "https://api.weather.gov/alerts/NWS-IDP-PROD-4035727-3424610",
                "identifier": "NWS-IDP-PROD-4035727-3424610",
                "sender": "w-nws.webmaster@noaa.gov",
                "sent": "2020-02-02T16:52:00-08:00"
            },
            {
                "@id": "https://api.weather.gov/alerts/NWS-IDP-PROD-4035727-3424612",
                "identifier": "NWS-IDP-PROD-4035727-3424612",
                "sender": "w-nws.webmaster@noaa.gov",
                "sent": "2020-02-02T16:52:00-08:00"
            },
            {
                "@id": "https://api.weather.gov/alerts/NWS-IDP-PROD-4035727-3424611",
                "identifier": "NWS-IDP-PROD-4035727-3424611",
                "sender": "w-nws.webmaster@noaa.gov",
                "sent": "2020-02-02T16:52:00-08:00"
            },
            {
                "@id": "https://api.weather.gov/alerts/NWS-IDP-PROD-4035486-3424311",
                "identifier": "NWS-IDP-PROD-4035486-3424311",
                "sender": "w-nws.webmaster@noaa.gov",
                "sent": "2020-02-02T13:13:00-08:00"
            },
            {
                "@id": "https://api.weather.gov/alerts/NWS-IDP-PROD-4035486-3424310",
                "identifier": "NWS-IDP-PROD-4035486-3424310",
                "sender": "w-nws.webmaster@noaa.gov",
                "sent": "2020-02-02T13:13:00-08:00"
            },
            {
                "@id": "https://api.weather.gov/alerts/NWS-IDP-PROD-4035486-3424312",
                "identifier": "NWS-IDP-PROD-4035486-3424312",
                "sender": "w-nws.webmaster@noaa.gov",
                "sent": "2020-02-02T13:13:00-08:00"
            },
            {
                "@id": "https://api.weather.gov/alerts/NWS-IDP-PROD-4036342-3425223",
                "identifier": "NWS-IDP-PROD-4036342-3425223",
                "sender": "w-nws.webmaster@noaa.gov",
                "sent": "2020-02-03T05:07:00-08:00"
            },
            {
                "@id": "https://api.weather.gov/alerts/NWS-IDP-PROD-4036342-3425225",
                "identifier": "NWS-IDP-PROD-4036342-3425225",
                "sender": "w-nws.webmaster@noaa.gov",
                "sent": "2020-02-03T05:07:00-08:00"
            },
            {
                "@id": "https://api.weather.gov/alerts/NWS-IDP-PROD-4036342-3425224",
                "identifier": "NWS-IDP-PROD-4036342-3425224",
                "sender": "w-nws.webmaster@noaa.gov",
                "sent": "2020-02-03T05:07:00-08:00"
            },
            {
                "@id": "https://api.weather.gov/alerts/NWS-IDP-PROD-4035976-3424828",
                "identifier": "NWS-IDP-PROD-4035976-3424828",
                "sender": "w-nws.webmaster@noaa.gov",
                "sent": "2020-02-02T22:03:00-08:00"
            },
            {
                "@id": "https://api.weather.gov/alerts/NWS-IDP-PROD-4035976-3424830",
                "identifier": "NWS-IDP-PROD-4035976-3424830",
                "sender": "w-nws.webmaster@noaa.gov",
                "sent": "2020-02-02T22:03:00-08:00"
            },
            {
                "@id": "https://api.weather.gov/alerts/NWS-IDP-PROD-4035976-3424829",
                "identifier": "NWS-IDP-PROD-4035976-3424829",
                "sender": "w-nws.webmaster@noaa.gov",
                "sent": "2020-02-02T22:03:00-08:00"
            },
            {
                "@id": "https://api.weather.gov/alerts/NWS-IDP-PROD-4036579-3425437",
                "identifier": "NWS-IDP-PROD-4036579-3425437",
                "sender": "w-nws.webmaster@noaa.gov",
                "sent": "2020-02-03T09:18:00-08:00"
            },
            {
                "@id": "https://api.weather.gov/alerts/NWS-IDP-PROD-4036579-3425436",
                "identifier": "NWS-IDP-PROD-4036579-3425436",
                "sender": "w-nws.webmaster@noaa.gov",
                "sent": "2020-02-03T09:18:00-08:00"
            },
            {
                "@id": "https://api.weather.gov/alerts/NWS-IDP-PROD-4036579-3425438",
                "identifier": "NWS-IDP-PROD-4036579-3425438",
                "sender": "w-nws.webmaster@noaa.gov",
                "sent": "2020-02-03T09:18:00-08:00"
            }
        ],
        "sent": "2020-02-03T12:06:00-08:00",
        "effective": "2020-02-03T12:06:00-08:00",
        "onset": "2020-02-05T01:00:00-08:00",
        "expires": "2020-02-03T23:00:00-08:00",
        "ends": "2020-02-05T09:00:00-08:00",
        "status": "Actual",
        "messageType": "Update",
        "category": "Met",
        "severity": "Severe",
        "certainty": "Possible",
        "urgency": "Future",
        "event": "Freeze Watch",
        "sender": "w-nws.webmaster@noaa.gov",
        "senderName": "NWS Los Angeles/Oxnard CA",
        "headline": "Freeze Watch issued February 3 at 12:06PM PST until February 5 at 9:00AM PST by NWS Los Angeles/Oxnard CA",
        "description": "* WHAT...For the Freeze Warning, sub-freezing temperatures as\nlow as 31 expected. For the Wind Advisory, northeast winds 20\nto 30 mph with gusts up to 45 mph expected. For the Freeze\nWatch, sub-freezing temperatures as low as 33 possible.\n\n* WHERE...San Fernando Valley.\n\n* WHEN...For the Freeze Warning, from 1 AM to 9 AM PST Tuesday.\nFor the Wind Advisory, from 9 PM this evening to 3 PM PST\nTuesday. For the Freeze Watch, from late Tuesday night through\nWednesday morning.\n\n* IMPACTS...Gusty winds will blow around unsecured objects and\nmake driving difficult, especially for high profile vehicles.\nTree limbs could be blown down and a few power outages may\nresult. Frost and freeze conditions will kill crops and other\nsensitive vegetation. Extended exposure to cold can cause\nhypothermia for animals and people. Vehicle windshields will\nbe frosted.",
        "instruction": "Use extra caution when driving, especially if operating a high\nprofile vehicle. Secure outdoor objects.\n\nTake steps now to protect tender plants from the cold. Plan for\nextra time to defrost vehicle windshields.",
        "response": "Prepare",
        "parameters": {
            "NWSheadline": [
                "WIND ADVISORY IN EFFECT FROM 9 PM THIS EVENING TO 3 PM PST TUESDAY... ...FREEZE WARNING IN EFFECT FROM 1 AM TO 9 AM PST TUESDAY... ...FREEZE WATCH REMAINS IN EFFECT FROM LATE TUESDAY NIGHT THROUGH WEDNESDAY MORNING"
            ],
            "VTEC": [
                "/O.CON.KLOX.FZ.A.0003.200205T0900Z-200205T1700Z/"
            ],
            "PIL": [
                "LOXNPWLOX"
            ],
            "BLOCKCHANNEL": [
                "CMAS",
                "EAS",
                "NWEM"
            ],
            "eventEndingTime": [
                "2020-02-05T09:00:00-08:00"
            ]
        }
    }
}