{
    "id": "https://api.weather.gov/alerts/NWS-IDP-PROD-4061036-3447244",
    "type": "Feature",
    "geometry": null,
    "properties": {
        "@id": "https://api.weather.gov/alerts/NWS-IDP-PROD-4061036-3447244",
        "@type": "wx:Alert",
        "id": "NWS-IDP-PROD-4061036-3447244",
        "areaDesc": "Coastal waters from Parramore Island to Cape Charles Light VA out 20 nm",
        "geocode": {
            "UGC": [
                "ANZ654"
            ],
            "SAME": [
                "073654"
            ]
        },
        "affectedZones": [
            "https://api.weather.gov/zones/forecast/ANZ654"
        ],
        "references": [
            {
                "@id": "https://api.weather.gov/alerts/NWS-IDP-PROD-4058342-3445045",
                "identifier": "NWS-IDP-PROD-4058342-3445045",
                "sender": "w-nws.webmaster@noaa.gov",
                "sent": "2020-02-13T12:41:00-05:00"
            },
            {
                "@id": "https://api.weather.gov/alerts/NWS-IDP-PROD-4059481-3445968",
                "identifier": "NWS-IDP-PROD-4059481-3445968",
                "sender": "w-nws.webmaster@noaa.gov",
                "sent": "2020-02-14T03:30:00-05:00"
            },
            {
                "@id": "https://api.weather.gov/alerts/NWS-IDP-PROD-4060301-3446653",
                "identifier": "NWS-IDP-PROD-4060301-3446653",
                "sender": "w-nws.webmaster@noaa.gov",
                "sent": "2020-02-14T14:11:00-05:00"
            },
            {
                "@id": "https://api.weather.gov/alerts/NWS-IDP-PROD-4058860-3445472",
                "identifier": "NWS-IDP-PROD-4058860-3445472",
                "sender": "w-nws.webmaster@noaa.gov",
                "sent": "2020-02-13T18:27:00-05:00"
            },
            {
                "@id": "https://api.weather.gov/alerts/NWS-IDP-PROD-4055335-3442378",
                "identifier": "NWS-IDP-PROD-4055335-3442378",
                "sender": "w-nws.webmaster@noaa.gov",
                "sent": "2020-02-12T09:14:00-05:00"
            },
            {
                "@id": "https://api.weather.gov/alerts/NWS-IDP-PROD-4059760-3446173",
                "identifier": "NWS-IDP-PROD-4059760-3446173",
                "sender": "w-nws.webmaster@noaa.gov",
                "sent": "2020-02-14T06:38:00-05:00"
            },
            {
                "@id": "https://api.weather.gov/alerts/NWS-IDP-PROD-4057226-3444141",
                "identifier": "NWS-IDP-PROD-4057226-3444141",
                "sender": "w-nws.webmaster@noaa.gov",
                "sent": "2020-02-13T02:35:00-05:00"
            },
            {
                "@id": "https://api.weather.gov/alerts/NWS-IDP-PROD-4057823-3444606",
                "identifier": "NWS-IDP-PROD-4057823-3444606",
                "sender": "w-nws.webmaster@noaa.gov",
                "sent": "2020-02-13T09:16:00-05:00"
            },
            {
                "@id": "https://api.weather.gov/alerts/NWS-IDP-PROD-4060621-3446899",
                "identifier": "NWS-IDP-PROD-4060621-3446899",
                "sender": "w-nws.webmaster@noaa.gov",
                "sent": "2020-02-14T18:39:00-05:00"
            },
            {
                "@id": "https://api.weather.gov/alerts/NWS-IDP-PROD-4056774-3443770",
                "identifier": "NWS-IDP-PROD-4056774-3443770",
                "sender": "w-nws.webmaster@noaa.gov",
                "sent": "2020-02-12T20:43:00-05:00"
            },
            {
                "@id": "https://api.weather.gov/alerts/NWS-IDP-PROD-4058612-3445286",
                "identifier": "NWS-IDP-PROD-4058612-3445286",
                "sender": "w-nws.webmaster@noaa.gov",
                "sent": "2020-02-13T15:12:00-05:00"
            },
            {
                "@id": "https://api.weather.gov/alerts/NWS-IDP-PROD-4056020-3443064",
                "identifier": "NWS-IDP-PROD-4056020-3443064",
                "sender": "w-nws.webmaster@noaa.gov",
                "sent": "2020-02-12T15:22:00-05:00"
            },
            {
                "@id": "https://api.weather.gov/alerts/NWS-IDP-PROD-4055794-3442822",
                "identifier": "NWS-IDP-PROD-4055794-3442822",
                "sender": "w-nws.webmaster@noaa.gov",
                "sent": "2020-02-12T12:46:00-05:00"
            },
            {
                "@id": "https://api.weather.gov/alerts/NWS-IDP-PROD-4054774-3441787",
                "identifier": "NWS-IDP-PROD-4054774-3441787",
                "sender": "w-nws.webmaster@noaa.gov",
                "sent": "2020-02-12T02:24:00-05:00"
            },
            {
                "@id": "https://api.weather.gov/alerts/NWS-IDP-PROD-4059372-3445893",
                "identifier": "NWS-IDP-PROD-4059372-3445893",
                "sender": "w-nws.webmaster@noaa.gov",
                "sent": "2020-02-14T00:09:00-05:00"
            },
            {
                "@id": "https://api.weather.gov/alerts/NWS-IDP-PROD-4059926-3446320",
                "identifier": "NWS-IDP-PROD-4059926-3446320",
                "sender": "w-nws.webmaster@noaa.gov",
                "sent": "2020-02-14T09:50:00-05:00"
            }
        ],
        "sent": "2020-02-15T00:27:00-05:00",
        "effective": "2020-02-15T00:27:00-05:00",
        "onset": "2020-02-15T00:27:00-05:00",
        "expires": "2020-02-15T04:00:00-05:00",
        "ends": "2020-02-15T04:00:00-05:00",
        "status": "Actual",
        "messageType": "Update",
        "category": "Met",
        "severity": "Minor",
        "certainty": "Likely",
        "urgency": "Expected",
        "event": "Small Craft Advisory",
        "sender": "w-nws.webmaster@noaa.gov",
        "senderName": "NWS Wakefield VA",
        "headline": "Small Craft Advisory issued February 15 at 12:27AM EST until February 15 at 4:00AM EST by NWS Wakefield VA",
        "description": "* WHAT...North winds 15 to 25 kt. Seas 3 to 5 ft.\n\n* WHERE...Coastal waters from Parramore Island to Cape Charles\nLight VA out 20 nm.\n\n* WHEN...Until 4 AM EST early this morning.\n\n* IMPACTS...Conditions will be hazardous to small craft.",
        "instruction": "Inexperienced mariners, especially those operating smaller\nvessels, should avoid navigating in hazardous conditions.",
        "response": "Avoid",
        "parameters": {
            "NWSheadline": [
                "SMALL CRAFT ADVISORY NOW IN EFFECT UNTIL 4 AM EST EARLY THIS MORNING"
            ],
            "VTEC": [
                "/O.EXT.KAKQ.SC.Y.0015.000000T0000Z-200215T0900Z/"
            ],
            "PIL": [
                "AKQMWWAKQ"
            ],
            "BLOCKCHANNEL": [
                "CMAS",
                "EAS",
                "NWEM"
            ],
            "eventEndingTime": [
                "2020-02-15T04:00:00-05:00"
            ]
        }
    }
}