{
    "id": "https://api.weather.gov/alerts/NWS-IDP-PROD-4009881-3402835",
    "type": "Feature",
    "geometry": null,
    "properties": {
        "@id": "https://api.weather.gov/alerts/NWS-IDP-PROD-4009881-3402835",
        "@type": "wx:Alert",
        "id": "NWS-IDP-PROD-4009881-3402835",
        "areaDesc": "Siskiyou Mountains and Southern Oregon Cascades",
        "geocode": {
            "UGC": [
                "ORZ028"
            ],
            "SAME": [
                "041029",
                "041033",
                "041035"
            ]
        },
        "affectedZones": [
            "https://api.weather.gov/zones/forecast/ORZ028"
        ],
        "references": [
            {
                "@id": "https://api.weather.gov/alerts/NWS-IDP-PROD-4002756-3396876",
                "identifier": "NWS-IDP-PROD-4002756-3396876",
                "sender": "w-nws.webmaster@noaa.gov",
                "sent": "2020-01-11T14:07:00-08:00"
            },
            {
                "@id": "https://api.weather.gov/alerts/NWS-IDP-PROD-4002756-3396875",
                "identifier": "NWS-IDP-PROD-4002756-3396875",
                "sender": "w-nws.webmaster@noaa.gov",
                "sent": "2020-01-11T14:07:00-08:00"
            },
            {
                "@id": "https://api.weather.gov/alerts/NWS-IDP-PROD-3995808-3390471",
                "identifier": "NWS-IDP-PROD-3995808-3390471",
                "sender": "w-nws.webmaster@noaa.gov",
                "sent": "2020-01-09T16:56:00-08:00"
            },
            {
                "@id": "https://api.weather.gov/alerts/NWS-IDP-PROD-4007794-3401184",
                "identifier": "NWS-IDP-PROD-4007794-3401184",
                "sender": "w-nws.webmaster@noaa.gov",
                "sent": "2020-01-13T11:30:00-08:00"
            },
            {
                "@id": "https://api.weather.gov/alerts/NWS-IDP-PROD-4007794-3401185",
                "identifier": "NWS-IDP-PROD-4007794-3401185",
                "sender": "w-nws.webmaster@noaa.gov",
                "sent": "2020-01-13T11:30:00-08:00"
            },
            {
                "@id": "https://api.weather.gov/alerts/NWS-IDP-PROD-4005975-3399663",
                "identifier": "NWS-IDP-PROD-4005975-3399663",
                "sender": "w-nws.webmaster@noaa.gov",
                "sent": "2020-01-12T13:58:00-08:00"
            },
            {
                "@id": "https://api.weather.gov/alerts/NWS-IDP-PROD-4005975-3399664",
                "identifier": "NWS-IDP-PROD-4005975-3399664",
                "sender": "w-nws.webmaster@noaa.gov",
                "sent": "2020-01-12T13:58:00-08:00"
            },
            {
                "@id": "https://api.weather.gov/alerts/NWS-IDP-PROD-3996691-3391211",
                "identifier": "NWS-IDP-PROD-3996691-3391211",
                "sender": "w-nws.webmaster@noaa.gov",
                "sent": "2020-01-10T03:52:00-08:00"
            },
            {
                "@id": "https://api.weather.gov/alerts/NWS-IDP-PROD-4008082-3401385",
                "identifier": "NWS-IDP-PROD-4008082-3401385",
                "sender": "w-nws.webmaster@noaa.gov",
                "sent": "2020-01-13T13:32:00-08:00"
            },
            {
                "@id": "https://api.weather.gov/alerts/NWS-IDP-PROD-4008082-3401386",
                "identifier": "NWS-IDP-PROD-4008082-3401386",
                "sender": "w-nws.webmaster@noaa.gov",
                "sent": "2020-01-13T13:32:00-08:00"
            },
            {
                "@id": "https://api.weather.gov/alerts/NWS-IDP-PROD-4004932-3398833",
                "identifier": "NWS-IDP-PROD-4004932-3398833",
                "sender": "w-nws.webmaster@noaa.gov",
                "sent": "2020-01-12T04:07:00-08:00"
            },
            {
                "@id": "https://api.weather.gov/alerts/NWS-IDP-PROD-4004932-3398832",
                "identifier": "NWS-IDP-PROD-4004932-3398832",
                "sender": "w-nws.webmaster@noaa.gov",
                "sent": "2020-01-12T04:07:00-08:00"
            },
            {
                "@id": "https://api.weather.gov/alerts/NWS-IDP-PROD-3998053-3392425",
                "identifier": "NWS-IDP-PROD-3998053-3392425",
                "sender": "w-nws.webmaster@noaa.gov",
                "sent": "2020-01-10T13:41:00-08:00"
            },
            {
                "@id": "https://api.weather.gov/alerts/NWS-IDP-PROD-3995674-3390349",
                "identifier": "NWS-IDP-PROD-3995674-3390349",
                "sender": "w-nws.webmaster@noaa.gov",
                "sent": "2020-01-09T14:35:00-08:00"
            },
            {
                "@id": "https://api.weather.gov/alerts/NWS-IDP-PROD-3995674-3390350",
                "identifier": "NWS-IDP-PROD-3995674-3390350",
                "sender": "w-nws.webmaster@noaa.gov",
                "sent": "2020-01-09T14:35:00-08:00"
            },
            {
                "@id": "https://api.weather.gov/alerts/NWS-IDP-PROD-4000449-3394705",
                "identifier": "NWS-IDP-PROD-4000449-3394705",
                "sender": "w-nws.webmaster@noaa.gov",
                "sent": "2020-01-11T04:01:00-08:00"
            },
            {
                "@id": "https://api.weather.gov/alerts/NWS-IDP-PROD-4007084-3400612",
                "identifier": "NWS-IDP-PROD-4007084-3400612",
                "sender": "w-nws.webmaster@noaa.gov",
                "sent": "2020-01-13T03:31:00-08:00"
            },
            {
                "@id": "https://api.weather.gov/alerts/NWS-IDP-PROD-4007084-3400613",
                "identifier": "NWS-IDP-PROD-4007084-3400613",
                "sender": "w-nws.webmaster@noaa.gov",
                "sent": "2020-01-13T03:31:00-08:00"
            },
            {
                "@id": "https://api.weather.gov/alerts/NWS-IDP-PROD-4000799-3395035",
                "identifier": "NWS-IDP-PROD-4000799-3395035",
                "sender": "w-nws.webmaster@noaa.gov",
                "sent": "2020-01-11T06:26:00-08:00"
            },
            {
                "@id": "https://api.weather.gov/alerts/NWS-IDP-PROD-4009099-3402137",
                "identifier": "NWS-IDP-PROD-4009099-3402137",
                "sender": "w-nws.webmaster@noaa.gov",
                "sent": "2020-01-14T02:16:00-08:00"
            },
            {
                "@id": "https://api.weather.gov/alerts/NWS-IDP-PROD-4009099-3402136",
                "identifier": "NWS-IDP-PROD-4009099-3402136",
                "sender": "w-nws.webmaster@noaa.gov",
                "sent": "2020-01-14T02:16:00-08:00"
            }
        ],
        "sent": "2020-01-14T10:00:00-08:00",
        "effective": "2020-01-14T10:00:00-08:00",
        "onset": "2020-01-14T10:00:00-08:00",
        "expires": "2020-01-14T18:00:00-08:00",
        "ends": "2020-01-14T22:00:00-08:00",
        "status": "Actual",
        "messageType": "Update",
        "category": "Met",
        "severity": "Severe",
        "certainty": "Likely",
        "urgency": "Expected",
        "event": "Winter Storm Warning",
        "sender": "w-nws.webmaster@noaa.gov",
        "senderName": "NWS Medford OR",
        "headline": "Winter Storm Warning issued January 14 at 10:00AM PST until January 14 at 10:00PM PST by NWS Medford OR",
        "description": "...EXTENDED PERIOD OF WINTER WEATHER CONTINUES...\n\n.Snow showers will continue through this morning across southern\nOregon and northern California, including some light\naccumulations on the West Side valley floors. Snow will continue\nto accumulate through Tuesday before tapering off Tuesday\nevening. More snow is likely to impact the Mt Shasta region and\nKlamath Mountains late Wednesday and Wednesday night.\n\n* WHAT...Snow expected. Additional snow accumulations of 2 to 4\ninches. Winds gusting as high as 35 mph.\n\n* WHERE...The Winter Storm Warning covers the southern Oregon\nCascades, including Lake of the Woods, Howard Prairie, and\nHighways 66 and 140.\n\n* WHEN...For the Winter Storm Warning, until 10 PM PST Tuesday.\n\n* IMPACTS...Plan on slippery road conditions.\n\n* View the hazard area in detail at\nhttps://www.wrh.noaa.gov/mfr/HAZARD",
        "instruction": "* Travel is strongly discouraged because of dangerous conditions.\n\n* If you must travel, keep tire chains, a flashlight, blankets,\nfood, water, medications, and a fully charged phone with you.\n\n* The safest place during a winter storm is indoors.\n\n* A Winter Storm Warning means that severe winter weather is\noccurring and poses a threat to life and property. Take\nprotective action now.",
        "response": "Prepare",
        "parameters": {
            "NWSheadline": [
                "WINTER STORM WARNING REMAINS IN EFFECT UNTIL 10 PM PST THIS EVENING... ...WINTER WEATHER ADVISORY WILL EXPIRE AT 10 AM PST THIS MORNING"
            ],
            "HazardType": [
                "Snow"
            ],
            "VTEC": [
                "/O.CON.KMFR.WS.W.0001.000000T0000Z-200115T0600Z/"
            ],
            "EAS-ORG": [
                "WXR"
            ],
            "PIL": [
                "MFRWSWMFR"
            ],
            "BLOCKCHANNEL": [
                "CMAS",
                "EAS",
                "NWEM"
            ],
            "eventEndingTime": [
                "2020-01-14T22:00:00-08:00"
            ]
        }
    }
}