{
    "id": "https://api.weather.gov/alerts/NWS-IDP-PROD-3983800-3381623",
    "type": "Feature",
    "geometry": null,
    "properties": {
        "@id": "https://api.weather.gov/alerts/NWS-IDP-PROD-3983800-3381623",
        "@type": "wx:Alert",
        "id": "NWS-IDP-PROD-3983800-3381623",
        "areaDesc": "Lower Kobuk and Noatak Valleys",
        "geocode": {
            "UGC": [
                "AKZ208"
            ],
            "SAME": [
                "002185",
                "002188"
            ]
        },
        "affectedZones": [
            "https://api.weather.gov/zones/forecast/AKZ208"
        ],
        "references": [
            {
                "@id": "https://api.weather.gov/alerts/NWS-IDP-PROD-3976375-3376005",
                "identifier": "NWS-IDP-PROD-3976375-3376005",
                "sender": "w-nws.webmaster@noaa.gov",
                "sent": "2019-12-28T13:59:00-09:00"
            },
            {
                "@id": "https://api.weather.gov/alerts/NWS-IDP-PROD-3978296-3377498",
                "identifier": "NWS-IDP-PROD-3978296-3377498",
                "sender": "w-nws.webmaster@noaa.gov",
                "sent": "2019-12-29T14:15:00-09:00"
            },
            {
                "@id": "https://api.weather.gov/alerts/NWS-IDP-PROD-3974839-3374975",
                "identifier": "NWS-IDP-PROD-3974839-3374975",
                "sender": "w-nws.webmaster@noaa.gov",
                "sent": "2019-12-27T13:57:00-09:00"
            },
            {
                "@id": "https://api.weather.gov/alerts/NWS-IDP-PROD-3980868-3379432",
                "identifier": "NWS-IDP-PROD-3980868-3379432",
                "sender": "w-nws.webmaster@noaa.gov",
                "sent": "2019-12-30T18:59:00-09:00"
            },
            {
                "@id": "https://api.weather.gov/alerts/NWS-IDP-PROD-3982321-3380534",
                "identifier": "NWS-IDP-PROD-3982321-3380534",
                "sender": "w-nws.webmaster@noaa.gov",
                "sent": "2019-12-31T13:57:00-09:00"
            },
            {
                "@id": "https://api.weather.gov/alerts/NWS-IDP-PROD-3970638-3372109",
                "identifier": "NWS-IDP-PROD-3970638-3372109",
                "sender": "w-nws.webmaster@noaa.gov",
                "sent": "2019-12-24T14:20:00-09:00"
            },
            {
                "@id": "https://api.weather.gov/alerts/NWS-IDP-PROD-3970034-3371717",
                "identifier": "NWS-IDP-PROD-3970034-3371717",
                "sender": "w-nws.webmaster@noaa.gov",
                "sent": "2019-12-24T03:38:00-09:00"
            },
            {
                "@id": "https://api.weather.gov/alerts/NWS-IDP-PROD-3972053-3373090",
                "identifier": "NWS-IDP-PROD-3972053-3373090",
                "sender": "w-nws.webmaster@noaa.gov",
                "sent": "2019-12-25T13:07:00-09:00"
            },
            {
                "@id": "https://api.weather.gov/alerts/NWS-IDP-PROD-3968867-3370976",
                "identifier": "NWS-IDP-PROD-3968867-3370976",
                "sender": "w-nws.webmaster@noaa.gov",
                "sent": "2019-12-23T04:51:00-09:00"
            },
            {
                "@id": "https://api.weather.gov/alerts/NWS-IDP-PROD-3978927-3377938",
                "identifier": "NWS-IDP-PROD-3978927-3377938",
                "sender": "w-nws.webmaster@noaa.gov",
                "sent": "2019-12-29T21:27:00-09:00"
            },
            {
                "@id": "https://api.weather.gov/alerts/NWS-IDP-PROD-3975568-3375449",
                "identifier": "NWS-IDP-PROD-3975568-3375449",
                "sender": "w-nws.webmaster@noaa.gov",
                "sent": "2019-12-28T02:34:00-09:00"
            },
            {
                "@id": "https://api.weather.gov/alerts/NWS-IDP-PROD-3971396-3372614",
                "identifier": "NWS-IDP-PROD-3971396-3372614",
                "sender": "w-nws.webmaster@noaa.gov",
                "sent": "2019-12-25T03:05:00-09:00"
            },
            {
                "@id": "https://api.weather.gov/alerts/NWS-IDP-PROD-3983153-3381131",
                "identifier": "NWS-IDP-PROD-3983153-3381131",
                "sender": "w-nws.webmaster@noaa.gov",
                "sent": "2020-01-01T03:05:00-09:00"
            },
            {
                "@id": "https://api.weather.gov/alerts/NWS-IDP-PROD-3979534-3378397",
                "identifier": "NWS-IDP-PROD-3979534-3378397",
                "sender": "w-nws.webmaster@noaa.gov",
                "sent": "2019-12-30T03:07:00-09:00"
            },
            {
                "@id": "https://api.weather.gov/alerts/NWS-IDP-PROD-3969432-3371317",
                "identifier": "NWS-IDP-PROD-3969432-3371317",
                "sender": "w-nws.webmaster@noaa.gov",
                "sent": "2019-12-23T15:31:00-09:00"
            },
            {
                "@id": "https://api.weather.gov/alerts/NWS-IDP-PROD-3983690-3381516",
                "identifier": "NWS-IDP-PROD-3983690-3381516",
                "sender": "w-nws.webmaster@noaa.gov",
                "sent": "2020-01-01T12:14:00-09:00"
            },
            {
                "@id": "https://api.weather.gov/alerts/NWS-IDP-PROD-3982382-3380572",
                "identifier": "NWS-IDP-PROD-3982382-3380572",
                "sender": "w-nws.webmaster@noaa.gov",
                "sent": "2019-12-31T14:38:00-09:00"
            },
            {
                "@id": "https://api.weather.gov/alerts/NWS-IDP-PROD-3982701-3380800",
                "identifier": "NWS-IDP-PROD-3982701-3380800",
                "sender": "w-nws.webmaster@noaa.gov",
                "sent": "2019-12-31T19:19:00-09:00"
            },
            {
                "@id": "https://api.weather.gov/alerts/NWS-IDP-PROD-3973631-3374181",
                "identifier": "NWS-IDP-PROD-3973631-3374181",
                "sender": "w-nws.webmaster@noaa.gov",
                "sent": "2019-12-26T16:44:00-09:00"
            },
            {
                "@id": "https://api.weather.gov/alerts/NWS-IDP-PROD-3982882-3380937",
                "identifier": "NWS-IDP-PROD-3982882-3380937",
                "sender": "w-nws.webmaster@noaa.gov",
                "sent": "2019-12-31T23:13:00-09:00"
            },
            {
                "@id": "https://api.weather.gov/alerts/NWS-IDP-PROD-3980438-3379074",
                "identifier": "NWS-IDP-PROD-3980438-3379074",
                "sender": "w-nws.webmaster@noaa.gov",
                "sent": "2019-12-30T13:13:00-09:00"
            },
            {
                "@id": "https://api.weather.gov/alerts/NWS-IDP-PROD-3979985-3378723",
                "identifier": "NWS-IDP-PROD-3979985-3378723",
                "sender": "w-nws.webmaster@noaa.gov",
                "sent": "2019-12-30T07:48:00-09:00"
            },
            {
                "@id": "https://api.weather.gov/alerts/NWS-IDP-PROD-3973534-3374125",
                "identifier": "NWS-IDP-PROD-3973534-3374125",
                "sender": "w-nws.webmaster@noaa.gov",
                "sent": "2019-12-26T14:29:00-09:00"
            },
            {
                "@id": "https://api.weather.gov/alerts/NWS-IDP-PROD-3974170-3374499",
                "identifier": "NWS-IDP-PROD-3974170-3374499",
                "sender": "w-nws.webmaster@noaa.gov",
                "sent": "2019-12-27T03:16:00-09:00"
            },
            {
                "@id": "https://api.weather.gov/alerts/NWS-IDP-PROD-3972841-3373642",
                "identifier": "NWS-IDP-PROD-3972841-3373642",
                "sender": "w-nws.webmaster@noaa.gov",
                "sent": "2019-12-26T02:43:00-09:00"
            },
            {
                "@id": "https://api.weather.gov/alerts/NWS-IDP-PROD-3977368-3376749",
                "identifier": "NWS-IDP-PROD-3977368-3376749",
                "sender": "w-nws.webmaster@noaa.gov",
                "sent": "2019-12-29T03:10:00-09:00"
            },
            {
                "@id": "https://api.weather.gov/alerts/NWS-IDP-PROD-3981500-3379924",
                "identifier": "NWS-IDP-PROD-3981500-3379924",
                "sender": "w-nws.webmaster@noaa.gov",
                "sent": "2019-12-31T03:00:00-09:00"
            }
        ],
        "sent": "2020-01-01T14:09:00-09:00",
        "effective": "2020-01-01T14:09:00-09:00",
        "onset": "2020-01-01T14:09:00-09:00",
        "expires": "2020-01-02T06:00:00-09:00",
        "ends": "2020-01-04T18:00:00-09:00",
        "status": "Actual",
        "messageType": "Update",
        "category": "Met",
        "severity": "Moderate",
        "certainty": "Likely",
        "urgency": "Expected",
        "event": "Wind Chill Advisory",
        "sender": "w-nws.webmaster@noaa.gov",
        "senderName": "NWS Fairbanks, AK",
        "headline": "Wind Chill Advisory issued January 1 at 2:09PM AKST until January 4 at 6:00PM AKST by NWS Fairbanks, AK",
        "description": "* WHAT...Very cold wind chills expected. The cold wind chills will\ncause frostbite in as little as 10 minutes to exposed skin.\nExpect wind chills as cod as 45 below zero.\n\n* WHERE...Lower Kobuk and Noatak Valleys.\n\n* WHEN...Now to 6 PM Saturday.\n\n* ADDITIONAL DETAILS...The strongest winds and coldest wind\nchills will be north of Noatak Village.",
        "instruction": "A Wind Chill Advisory means that cold air and sustained wind\nspeeds of 15 mph or more will create low wind chills. Frost bite\nand hypothermia can occur if precautions are not taken.",
        "response": "Prepare",
        "parameters": {
            "NWSheadline": [
                "WIND CHILL ADVISORY NOW IN EFFECT UNTIL 6 PM AKST SATURDAY"
            ],
            "HazardType": [
                "Wind Chill"
            ],
            "VTEC": [
                "/O.EXT.PAFG.WC.Y.0020.000000T0000Z-200105T0300Z/"
            ],
            "PIL": [
                "WCZWSWWCZ"
            ],
            "BLOCKCHANNEL": [
                "CMAS",
                "EAS",
                "NWEM"
            ],
            "eventEndingTime": [
                "2020-01-04T18:00:00-09:00"
            ]
        }
    }
}